README.md
setup.py
distributions_oren/Binomialdistribution.py
distributions_oren/Gaussiandistribution.py
distributions_oren/Generaldistribution.py
distributions_oren/__init__.py
distributions_oren.egg-info/PKG-INFO
distributions_oren.egg-info/SOURCES.txt
distributions_oren.egg-info/dependency_links.txt
distributions_oren.egg-info/not-zip-safe
distributions_oren.egg-info/top_level.txt